magnus/__init__.py
magnus/cli/__init__.py
magnus/cli/commands.py
magnus/cli/main.py
magnus_sdk-0.2.4.dist-info/METADATA
magnus_sdk-0.2.4.dist-info/WHEEL
magnus_sdk-0.2.4.dist-info/entry_points.txt
magnus_sdk-0.2.4.dist-info/RECORD
