Metadata-Version: 2.4
Name: magnus-sdk
Version: 0.2.4
Summary: Official Python SDK and CLI for Magnus
Author-email: "Magnus Team, Rise-AGI" <sun_retailer@163.com>
Requires-Python: >=3.10
Requires-Dist: httpx[socks]>=0.27.0
Requires-Dist: pydantic>=2.0.0
Requires-Dist: python-dotenv>=1.0.0
Requires-Dist: rich>=13.0.0
Requires-Dist: ruamel-yaml>=0.18.0
Requires-Dist: typer>=0.9.0
